CHANGES.txt
LICENSE.txt
MANIFEST.in
README.txt
setup.py
docx_xslt.egg-info/PKG-INFO
docx_xslt.egg-info/SOURCES.txt
docx_xslt.egg-info/dependency_links.txt
docx_xslt.egg-info/requires.txt
docx_xslt.egg-info/top_level.txt
docxxslt/__init__.py
docxxslt/engines.py
docxxslt/namespaces.py
docxxslt/nodes.py
docxxslt/package.py
docxxslt/utils.py
docxxslt/xsl.py