Metadata-Version: 1.1
Name: docx-xslt
Version: 1.0.4
Summary: XSL transformation for Microsoft Word .docx files
Home-page: https://github.com/backbohne/docx-xslt
Author: Frank Bohnsack
Author-email: frank.bohnsack@gmail.com
License: The MIT License (MIT)
